MANIFEST.in
base_report_designer_installer.xml
setup.py
./__init__.py
./__openerp__.py
./base_report_designer.py
./installer.py
./openerp_sxw2rml/__init__.py
./openerp_sxw2rml/openerp_sxw2rml.py
./wizard/__init__.py
./wizard/base_report_designer_modify.py
i18n/ar.po
i18n/base_report_designer.pot
i18n/bg.po
i18n/bs.po
i18n/ca.po
i18n/cs.po
i18n/da.po
i18n/de.po
i18n/el.po
i18n/en_GB.po
i18n/es.po
i18n/es_AR.po
i18n/es_CR.po
i18n/es_EC.po
i18n/es_MX.po
i18n/es_PY.po
i18n/es_VE.po
i18n/et.po
i18n/fa.po
i18n/fi.po
i18n/fr.po
i18n/gl.po
i18n/hi.po
i18n/hr.po
i18n/hu.po
i18n/id.po
i18n/it.po
i18n/ja.po
i18n/ko.po
i18n/lt.po
i18n/mk.po
i18n/mn.po
i18n/nb.po
i18n/nl.po
i18n/nl_BE.po
i18n/pl.po
i18n/pt.po
i18n/pt_BR.po
i18n/ro.po
i18n/ru.po
i18n/sk.po
i18n/sl.po
i18n/sq.po
i18n/sr.po
i18n/sr@latin.po
i18n/sv.po
i18n/tlh.po
i18n/tr.po
i18n/uk.po
i18n/vi.po
i18n/zh_CN.po
i18n/zh_TW.po
images/base_report_designer1.jpeg
images/base_report_designer2.jpeg
openerp_base_report_designer.egg-info/PKG-INFO
openerp_base_report_designer.egg-info/SOURCES.txt
openerp_base_report_designer.egg-info/dependency_links.txt
openerp_base_report_designer.egg-info/requires.txt
openerp_base_report_designer.egg-info/top_level.txt
openerp_sxw2rml/normalized_odt2rml.xsl
openerp_sxw2rml/normalized_oo2rml.xsl
plugin/openerp_report_designer/bin/package/images/About.jpg
plugin/openerp_report_designer/bin/package/images/aboutus_b.png
plugin/openerp_report_designer/bin/package/images/aboutus_s.png
plugin/openerp_report_designer/bin/package/images/convetBtoF_b.png
plugin/openerp_report_designer/bin/package/images/convetBtoF_s.png
plugin/openerp_report_designer/bin/package/images/convetFtoB_b.png
plugin/openerp_report_designer/bin/package/images/convetFtoB_s.png
plugin/openerp_report_designer/bin/package/images/export_rml_b.png
plugin/openerp_report_designer/bin/package/images/export_rml_s.png
plugin/openerp_report_designer/bin/package/images/expression_b.png
plugin/openerp_report_designer/bin/package/images/expression_s.png
plugin/openerp_report_designer/bin/package/images/field_b.png
plugin/openerp_report_designer/bin/package/images/field_s.png
plugin/openerp_report_designer/bin/package/images/lang_b.png
